mcecli/__init__.py
mcecli/client.py
mcecli/config.py
mcecli/exceptions.py
mcecli/main.py
mcecli/utils.py
mcecli/commands/__init__.py
mcecli/commands/compute_config.py
mcecli/commands/config.py
mcecli/commands/example.py
mcecli/commands/job.py
mcecli/commands/logs.py
mcecli/commands/project.py
mcecli/commands/queue.py
mcecli/commands/upload.py
mcecli-0.1.2.dist-info/METADATA
mcecli-0.1.2.dist-info/WHEEL
mcecli-0.1.2.dist-info/entry_points.txt
mcecli-0.1.2.dist-info/licenses/LICENSE
mcecli-0.1.2.dist-info/RECORD
