Metadata-Version: 2.4
Name: mcecli
Version: 0.1.2
Summary: MCE Server Python CLI Client - A command-line interface for managing multi-modal compute engine resources
Project-URL: Homepage, https://github.com/your-org/mce-server
Project-URL: Documentation, https://github.com/your-org/mce-server/blob/main/mcecli/README.md
Project-URL: Repository, https://github.com/your-org/mce-server.git
Project-URL: Bug Tracker, https://github.com/your-org/mce-server/issues
Project-URL: Changelog, https://github.com/your-org/mce-server/blob/main/CHANGELOG.md
Author-email: MCE Team <mce@example.com>
Maintainer-email: MCE Team <mce@example.com>
License: MIT
License-File: LICENSE
Keywords: cli,compute-engine,distributed-computing,kubernetes,machine-learning,mce,ray
Classifier: Development Status :: 4 - Beta
Classifier: Environment :: Console
Classifier: Intended Audience :: Developers
Classifier: Intended Audience :: System Administrators
Classifier: License :: OSI Approved :: MIT License
Classifier: Operating System :: OS Independent
Classifier: Programming Language :: Python :: 3
Classifier: Programming Language :: Python :: 3.9
Classifier: Programming Language :: Python :: 3.10
Classifier: Programming Language :: Python :: 3.11
Classifier: Programming Language :: Python :: 3.12
Classifier: Topic :: Software Development :: Libraries :: Python Modules
Classifier: Topic :: System :: Distributed Computing
Classifier: Topic :: System :: Systems Administration
Classifier: Topic :: Utilities
Requires-Python: >=3.9
Requires-Dist: click>=8.0.0
Requires-Dist: cos-python-sdk-v5>=1.9.41
Requires-Dist: pyyaml>=6.0
Requires-Dist: requests>=2.25.0
Requires-Dist: rich>=10.0.0
Requires-Dist: tabulate>=0.9.0
Requires-Dist: websocket-client>=1.0.0
Provides-Extra: dev
Requires-Dist: black>=23.0.0; extra == 'dev'
Requires-Dist: flake8>=6.0.0; extra == 'dev'
Requires-Dist: isort>=5.12.0; extra == 'dev'
Requires-Dist: mypy>=1.0.0; extra == 'dev'
Requires-Dist: pytest-cov>=4.0.0; extra == 'dev'
Requires-Dist: pytest>=7.0.0; extra == 'dev'
